restfullmonkey/__init__.py
restfullmonkey/__main__.py
restfullmonkey/arg.py
restfullmonkey/cli.py
restfullmonkey/conf.py
restfullmonkey/database.py
restfullmonkey/databasedbm.py
restfullmonkey/databasehelp.py
restfullmonkey/databasejson.py
restfullmonkey/indexes.py
restfullmonkey/indexesdbm.py
restfullmonkey/log.py
restfullmonkey/pathes.py
restfullmonkey/pathesdbm.py
restfullmonkey/server.py
restfullmonkey-0.0.1.dist-info/licenses/LICENSE
restfullmonkey-0.0.1.dist-info/WHEEL
restfullmonkey-0.0.1.dist-info/METADATA
restfullmonkey-0.0.1.dist-info/RECORD
